clickme/__init__.py
clickme/admin.py
clickme/apps.py
clickme/config.py
clickme/methods.py
clickme/models.py
clickme/serializers.py
clickme/tests.py
clickme/urls.py
clickme/views.py
clickme/migrations/__init__.py
clickme-1.0.dist-info/LICENSE
clickme-1.0.dist-info/METADATA
clickme-1.0.dist-info/WHEEL
clickme-1.0.dist-info/top_level.txt
clickme-1.0.dist-info/RECORD
