Metadata-Version: 2.1
Name: clickme
Version: 1.0
Summary: clickme
Home-page: https://github.com/rajab-murod/clickme
Author: rajab-murod
Author-email: rajab.murod1995@gmail.com
License: UNKNOWN
Platform: UNKNOWN
Classifier: Programming Language :: Python :: 3
Classifier: License :: OSI Approved :: MIT License
Requires-Python: >=3.5
Requires-Dist: requests
Requires-Dist: django
Requires-Dist: djangorestframework
